significantdigits/__init__.py
significantdigits/__main__.py
significantdigits/_significantdigits.py
significantdigits/args.py
significantdigits/export/__init__.py
significantdigits/export/generic.py
significantdigits/export/numpy.py
significantdigits/export/stdin.py
significantdigits/stats/__init__.py
significantdigits/stats/dense.py
significantdigits/stats/dispatch.py
significantdigits/stats/sparse.py
significantdigits-0.4.0.dist-info/METADATA
significantdigits-0.4.0.dist-info/WHEEL
significantdigits-0.4.0.dist-info/entry_points.txt
significantdigits-0.4.0.dist-info/licenses/LICENSE
significantdigits-0.4.0.dist-info/RECORD
