Metadata-Version: 2.4
Name: significantdigits
Version: 0.4.0
Summary: Solid stochastic statistic analysis of Stochastic Arithmetic
Project-URL: Bug Tracker, https://github.com/verificarlo/significantdigits/issues
Author-email: Verificarlo contributors <verificarlo@googlegroups.com>
License: Copyright 2022 Verificarlo project
License-File: LICENSE
Classifier: Development Status :: 4 - Beta
Classifier: License :: OSI Approved :: Apache Software License
Classifier: Operating System :: POSIX :: Linux
Classifier: Programming Language :: Python :: 3
Classifier: Topic :: Scientific/Engineering :: Information Analysis
Requires-Python: >=3.8
Requires-Dist: attrs>=21.2.0
Requires-Dist: icecream>=2.1.3
Requires-Dist: iniconfig>=1.1.1
Requires-Dist: numpy>=1.22.0
Requires-Dist: packaging>=21.2
Requires-Dist: pdoc>=14.2.0
Requires-Dist: pluggy>=1.0.0
Requires-Dist: py>=1.10.0
Requires-Dist: pyparsing>=2.4.7
Requires-Dist: pytest>=6.2.5
Requires-Dist: scipy>=1.7.3
Requires-Dist: toml>=0.10.2
